{
    "object_alias": "exface.Core.ATTRIBUTE",
    "columns": [
        {
            "name": "CREATED_ON",
            "attribute_alias": "CREATED_ON"
        },
        {
            "name": "MODIFIED_ON",
            "attribute_alias": "MODIFIED_ON"
        },
        {
            "name": "CREATED_BY_USER",
            "attribute_alias": "CREATED_BY_USER"
        },
        {
            "name": "MODIFIED_BY_USER",
            "attribute_alias": "MODIFIED_BY_USER"
        },
        {
            "name": "UID",
            "attribute_alias": "UID"
        },
        {
            "name": "SORTABLEFLAG",
            "attribute_alias": "SORTABLEFLAG"
        },
        {
            "name": "FILTERABLEFLAG",
            "attribute_alias": "FILTERABLEFLAG"
        },
        {
            "name": "AGGREGATABLEFLAG",
            "attribute_alias": "AGGREGATABLEFLAG"
        },
        {
            "name": "DEFAULT_AGGREGATE_FUNCTION",
            "attribute_alias": "DEFAULT_AGGREGATE_FUNCTION"
        },
        {
            "name": "VALUE_LIST_DELIMITER",
            "attribute_alias": "VALUE_LIST_DELIMITER"
        },
        {
            "name": "READABLEFLAG",
            "attribute_alias": "READABLEFLAG"
        },
        {
            "name": "WRITABLEFLAG",
            "attribute_alias": "WRITABLEFLAG"
        },
        {
            "name": "SYSTEMFLAG",
            "attribute_alias": "SYSTEMFLAG"
        },
        {
            "name": "DEFAULT_EDITOR_UXON",
            "attribute_alias": "DEFAULT_EDITOR_UXON"
        },
        {
            "name": "COPY_WITH_RELATED_OBJECT",
            "attribute_alias": "COPY_WITH_RELATED_OBJECT"
        },
        {
            "name": "DELETE_WITH_RELATED_OBJECT",
            "attribute_alias": "DELETE_WITH_RELATED_OBJECT"
        },
        {
            "name": "DEFAULT_DISPLAY_UXON",
            "attribute_alias": "DEFAULT_DISPLAY_UXON"
        },
        {
            "name": "COMMENTS",
            "attribute_alias": "COMMENTS"
        },
        {
            "name": "NAME",
            "attribute_alias": "NAME"
        },
        {
            "name": "RELATION_CARDINALITY",
            "attribute_alias": "RELATION_CARDINALITY"
        },
        {
            "name": "TYPE",
            "attribute_alias": "TYPE"
        },
        {
            "name": "COPYABLEFLAG",
            "attribute_alias": "COPYABLEFLAG"
        },
        {
            "name": "ALIAS",
            "attribute_alias": "ALIAS"
        },
        {
            "name": "DATATYPE",
            "attribute_alias": "DATATYPE"
        },
        {
            "name": "DATA_ADDRESS",
            "attribute_alias": "DATA_ADDRESS"
        },
        {
            "name": "OBJECT",
            "attribute_alias": "OBJECT"
        },
        {
            "name": "FORMATTER",
            "attribute_alias": "FORMATTER"
        },
        {
            "name": "DISPLAYORDER",
            "attribute_alias": "DISPLAYORDER"
        },
        {
            "name": "LABELFLAG",
            "attribute_alias": "LABELFLAG"
        },
        {
            "name": "UIDFLAG",
            "attribute_alias": "UIDFLAG"
        },
        {
            "name": "HIDDENFLAG",
            "attribute_alias": "HIDDENFLAG"
        },
        {
            "name": "EDITABLEFLAG",
            "attribute_alias": "EDITABLEFLAG"
        },
        {
            "name": "REQUIREDFLAG",
            "attribute_alias": "REQUIREDFLAG"
        },
        {
            "name": "RELATED_OBJ",
            "attribute_alias": "RELATED_OBJ"
        },
        {
            "name": "SORTERPOS",
            "attribute_alias": "SORTERPOS"
        },
        {
            "name": "SORTERDIR",
            "attribute_alias": "SORTERDIR"
        },
        {
            "name": "RELATED_OBJ_ATTR",
            "attribute_alias": "RELATED_OBJ_ATTR"
        },
        {
            "name": "SHORT_DESCRIPTION",
            "attribute_alias": "SHORT_DESCRIPTION"
        },
        {
            "name": "DATA_ADDRESS_PROPS",
            "attribute_alias": "DATA_ADDRESS_PROPS"
        },
        {
            "name": "DEFAULT_VALUE",
            "attribute_alias": "DEFAULT_VALUE"
        },
        {
            "name": "FIXED_VALUE",
            "attribute_alias": "FIXED_VALUE"
        },
        {
            "name": "CUSTOM_DATA_TYPE",
            "attribute_alias": "CUSTOM_DATA_TYPE"
        }
    ],
    "rows": [
        {
            "CREATED_ON": "2021-01-19 09:53:44",
            "MODIFIED_ON": "2021-01-19 09:55:00",
            "CREATED_BY_USER": "0x31000000000000000000000000000000",
            "MODIFIED_BY_USER": "0x31000000000000000000000000000000",
            "UID": "0x11eb9a00d61757c29a00847beb4a5184",
            "SORTABLEFLAG": "1",
            "FILTERABLEFLAG": "1",
            "AGGREGATABLEFLAG": "1",
            "DEFAULT_AGGREGATE_FUNCTION": "",
            "VALUE_LIST_DELIMITER": ",",
            "READABLEFLAG": "1",
            "WRITABLEFLAG": "0",
            "SYSTEMFLAG": "0",
            "DEFAULT_EDITOR_UXON": null,
            "COPY_WITH_RELATED_OBJECT": "0",
            "DELETE_WITH_RELATED_OBJECT": "0",
            "DEFAULT_DISPLAY_UXON": null,
            "COMMENTS": "",
            "NAME": "Subject",
            "RELATION_CARDINALITY": "",
            "TYPE": "D",
            "COPYABLEFLAG": "0",
            "ALIAS": "sub",
            "DATATYPE": "0x30000000000000000000000000000000",
            "DATA_ADDRESS": "sub",
            "OBJECT": "0x11ebad0505941fc8ad05847beb4a5184",
            "FORMATTER": "",
            "DISPLAYORDER": null,
            "LABELFLAG": "0",
            "UIDFLAG": "1",
            "HIDDENFLAG": "0",
            "EDITABLEFLAG": "0",
            "REQUIREDFLAG": "0",
            "RELATED_OBJ": "",
            "SORTERPOS": null,
            "SORTERDIR": "",
            "RELATED_OBJ_ATTR": "",
            "SHORT_DESCRIPTION": "Identifier for the End-User at the Issuer.",
            "DATA_ADDRESS_PROPS": null,
            "DEFAULT_VALUE": "",
            "FIXED_VALUE": "",
            "CUSTOM_DATA_TYPE": null
        },
        {
            "CREATED_ON": "2021-01-19 09:54:40",
            "MODIFIED_ON": "2021-01-19 09:54:40",
            "CREATED_BY_USER": "0x31000000000000000000000000000000",
            "MODIFIED_BY_USER": "0x31000000000000000000000000000000",
            "UID": "0x11eb9757f777011a9757847beb4a5184",
            "SORTABLEFLAG": "1",
            "FILTERABLEFLAG": "1",
            "AGGREGATABLEFLAG": "1",
            "DEFAULT_AGGREGATE_FUNCTION": "",
            "VALUE_LIST_DELIMITER": ",",
            "READABLEFLAG": "1",
            "WRITABLEFLAG": "0",
            "SYSTEMFLAG": "0",
            "DEFAULT_EDITOR_UXON": null,
            "COPY_WITH_RELATED_OBJECT": "0",
            "DELETE_WITH_RELATED_OBJECT": "0",
            "DEFAULT_DISPLAY_UXON": null,
            "COMMENTS": "",
            "NAME": "Name",
            "RELATION_CARDINALITY": "",
            "TYPE": "D",
            "COPYABLEFLAG": "0",
            "ALIAS": "name",
            "DATATYPE": "0x30000000000000000000000000000000",
            "DATA_ADDRESS": "name",
            "OBJECT": "0x11ebad0505941fc8ad05847beb4a5184",
            "FORMATTER": "",
            "DISPLAYORDER": null,
            "LABELFLAG": "1",
            "UIDFLAG": "0",
            "HIDDENFLAG": "0",
            "EDITABLEFLAG": "0",
            "REQUIREDFLAG": "0",
            "RELATED_OBJ": "",
            "SORTERPOS": null,
            "SORTERDIR": "",
            "RELATED_OBJ_ATTR": "",
            "SHORT_DESCRIPTION": "End-User's full name in displayable form including all name parts, possibly including titles and suffixes, ordered according to the End-User's locale and preferences.",
            "DATA_ADDRESS_PROPS": null,
            "DEFAULT_VALUE": "",
            "FIXED_VALUE": "",
            "CUSTOM_DATA_TYPE": null
        },
        {
            "CREATED_ON": "2021-01-21 18:01:51",
            "MODIFIED_ON": "2021-01-21 18:01:51",
            "CREATED_BY_USER": "0x31000000000000000000000000000000",
            "MODIFIED_BY_USER": "0x31000000000000000000000000000000",
            "UID": "0x11eb8a485b38280a8a48025041000001",
            "SORTABLEFLAG": "1",
            "FILTERABLEFLAG": "1",
            "AGGREGATABLEFLAG": "1",
            "DEFAULT_AGGREGATE_FUNCTION": "",
            "VALUE_LIST_DELIMITER": ",",
            "READABLEFLAG": "1",
            "WRITABLEFLAG": "0",
            "SYSTEMFLAG": "0",
            "DEFAULT_EDITOR_UXON": null,
            "COPY_WITH_RELATED_OBJECT": "0",
            "DELETE_WITH_RELATED_OBJECT": "0",
            "DEFAULT_DISPLAY_UXON": null,
            "COMMENTS": "",
            "NAME": "Given Name",
            "RELATION_CARDINALITY": "",
            "TYPE": "D",
            "COPYABLEFLAG": "0",
            "ALIAS": "given_name",
            "DATATYPE": "0x30000000000000000000000000000000",
            "DATA_ADDRESS": "given_name",
            "OBJECT": "0x11ebad0505941fc8ad05847beb4a5184",
            "FORMATTER": "",
            "DISPLAYORDER": null,
            "LABELFLAG": "0",
            "UIDFLAG": "0",
            "HIDDENFLAG": "0",
            "EDITABLEFLAG": "0",
            "REQUIREDFLAG": "0",
            "RELATED_OBJ": "",
            "SORTERPOS": null,
            "SORTERDIR": "",
            "RELATED_OBJ_ATTR": "",
            "SHORT_DESCRIPTION": "\tGiven name(s) or first name(s) of the End-User. Note that in some cultures, people can have multiple given names; all can be present, with the names being separated by space characters.",
            "DATA_ADDRESS_PROPS": null,
            "DEFAULT_VALUE": "",
            "FIXED_VALUE": "",
            "CUSTOM_DATA_TYPE": null
        },
        {
            "CREATED_ON": "2021-01-21 18:02:12",
            "MODIFIED_ON": "2021-01-21 18:02:12",
            "CREATED_BY_USER": "0x31000000000000000000000000000000",
            "MODIFIED_BY_USER": "0x31000000000000000000000000000000",
            "UID": "0x11eb8ffd67d0c5228ffd025041000001",
            "SORTABLEFLAG": "1",
            "FILTERABLEFLAG": "1",
            "AGGREGATABLEFLAG": "1",
            "DEFAULT_AGGREGATE_FUNCTION": "",
            "VALUE_LIST_DELIMITER": ",",
            "READABLEFLAG": "1",
            "WRITABLEFLAG": "0",
            "SYSTEMFLAG": "0",
            "DEFAULT_EDITOR_UXON": null,
            "COPY_WITH_RELATED_OBJECT": "0",
            "DELETE_WITH_RELATED_OBJECT": "0",
            "DEFAULT_DISPLAY_UXON": null,
            "COMMENTS": "",
            "NAME": "Family Name",
            "RELATION_CARDINALITY": "",
            "TYPE": "D",
            "COPYABLEFLAG": "0",
            "ALIAS": "family_name",
            "DATATYPE": "0x30000000000000000000000000000000",
            "DATA_ADDRESS": "family_name",
            "OBJECT": "0x11ebad0505941fc8ad05847beb4a5184",
            "FORMATTER": "",
            "DISPLAYORDER": null,
            "LABELFLAG": "0",
            "UIDFLAG": "0",
            "HIDDENFLAG": "0",
            "EDITABLEFLAG": "0",
            "REQUIREDFLAG": "0",
            "RELATED_OBJ": "",
            "SORTERPOS": null,
            "SORTERDIR": "",
            "RELATED_OBJ_ATTR": "",
            "SHORT_DESCRIPTION": "Surname(s) or last name(s) of the End-User. Note that in some cultures, people can have multiple family names or no family name; all can be present, with the names being separated by space characters.",
            "DATA_ADDRESS_PROPS": null,
            "DEFAULT_VALUE": "",
            "FIXED_VALUE": "",
            "CUSTOM_DATA_TYPE": null
        },
        {
            "CREATED_ON": "2021-01-21 18:02:35",
            "MODIFIED_ON": "2021-01-21 18:02:35",
            "CREATED_BY_USER": "0x31000000000000000000000000000000",
            "MODIFIED_BY_USER": "0x31000000000000000000000000000000",
            "UID": "0x11ebbc66757a3622bc66025041000001",
            "SORTABLEFLAG": "1",
            "FILTERABLEFLAG": "1",
            "AGGREGATABLEFLAG": "1",
            "DEFAULT_AGGREGATE_FUNCTION": "",
            "VALUE_LIST_DELIMITER": ",",
            "READABLEFLAG": "1",
            "WRITABLEFLAG": "0",
            "SYSTEMFLAG": "0",
            "DEFAULT_EDITOR_UXON": null,
            "COPY_WITH_RELATED_OBJECT": "0",
            "DELETE_WITH_RELATED_OBJECT": "0",
            "DEFAULT_DISPLAY_UXON": null,
            "COMMENTS": "",
            "NAME": "Middle Name",
            "RELATION_CARDINALITY": "",
            "TYPE": "D",
            "COPYABLEFLAG": "0",
            "ALIAS": "middle_name",
            "DATATYPE": "0x30000000000000000000000000000000",
            "DATA_ADDRESS": "middle_name",
            "OBJECT": "0x11ebad0505941fc8ad05847beb4a5184",
            "FORMATTER": "",
            "DISPLAYORDER": null,
            "LABELFLAG": "0",
            "UIDFLAG": "0",
            "HIDDENFLAG": "0",
            "EDITABLEFLAG": "0",
            "REQUIREDFLAG": "0",
            "RELATED_OBJ": "",
            "SORTERPOS": null,
            "SORTERDIR": "",
            "RELATED_OBJ_ATTR": "",
            "SHORT_DESCRIPTION": "Middle name(s) of the End-User. Note that in some cultures, people can have multiple middle names; all can be present, with the names being separated by space characters. Also note that in some cultures, middle names are not used.",
            "DATA_ADDRESS_PROPS": null,
            "DEFAULT_VALUE": "",
            "FIXED_VALUE": "",
            "CUSTOM_DATA_TYPE": null
        },
        {
            "CREATED_ON": "2021-01-21 18:03:05",
            "MODIFIED_ON": "2021-01-21 18:03:05",
            "CREATED_BY_USER": "0x31000000000000000000000000000000",
            "MODIFIED_BY_USER": "0x31000000000000000000000000000000",
            "UID": "0x11eba1a38759cb50a1a3025041000001",
            "SORTABLEFLAG": "1",
            "FILTERABLEFLAG": "1",
            "AGGREGATABLEFLAG": "1",
            "DEFAULT_AGGREGATE_FUNCTION": "",
            "VALUE_LIST_DELIMITER": ",",
            "READABLEFLAG": "1",
            "WRITABLEFLAG": "0",
            "SYSTEMFLAG": "0",
            "DEFAULT_EDITOR_UXON": null,
            "COPY_WITH_RELATED_OBJECT": "0",
            "DELETE_WITH_RELATED_OBJECT": "0",
            "DEFAULT_DISPLAY_UXON": null,
            "COMMENTS": "",
            "NAME": "Nickname",
            "RELATION_CARDINALITY": "",
            "TYPE": "D",
            "COPYABLEFLAG": "0",
            "ALIAS": "nickname",
            "DATATYPE": "0x30000000000000000000000000000000",
            "DATA_ADDRESS": "nickname",
            "OBJECT": "0x11ebad0505941fc8ad05847beb4a5184",
            "FORMATTER": "",
            "DISPLAYORDER": null,
            "LABELFLAG": "0",
            "UIDFLAG": "0",
            "HIDDENFLAG": "0",
            "EDITABLEFLAG": "0",
            "REQUIREDFLAG": "0",
            "RELATED_OBJ": "",
            "SORTERPOS": null,
            "SORTERDIR": "",
            "RELATED_OBJ_ATTR": "",
            "SHORT_DESCRIPTION": "Casual name of the End-User that may or may not be the same as the given_name. For instance, a nickname value of Mike might be returned alongside a given_name value of Michael.\n",
            "DATA_ADDRESS_PROPS": null,
            "DEFAULT_VALUE": "",
            "FIXED_VALUE": "",
            "CUSTOM_DATA_TYPE": null
        },
        {
            "CREATED_ON": "2021-01-21 18:03:50",
            "MODIFIED_ON": "2021-01-21 18:03:50",
            "CREATED_BY_USER": "0x31000000000000000000000000000000",
            "MODIFIED_BY_USER": "0x31000000000000000000000000000000",
            "UID": "0x11eb8376a20f00b48376025041000001",
            "SORTABLEFLAG": "1",
            "FILTERABLEFLAG": "1",
            "AGGREGATABLEFLAG": "1",
            "DEFAULT_AGGREGATE_FUNCTION": "",
            "VALUE_LIST_DELIMITER": ",",
            "READABLEFLAG": "1",
            "WRITABLEFLAG": "0",
            "SYSTEMFLAG": "0",
            "DEFAULT_EDITOR_UXON": null,
            "COPY_WITH_RELATED_OBJECT": "0",
            "DELETE_WITH_RELATED_OBJECT": "0",
            "DEFAULT_DISPLAY_UXON": null,
            "COMMENTS": "",
            "NAME": "Preferred Username",
            "RELATION_CARDINALITY": "",
            "TYPE": "D",
            "COPYABLEFLAG": "0",
            "ALIAS": "preferred_username",
            "DATATYPE": "0x30000000000000000000000000000000",
            "DATA_ADDRESS": "preferred_username",
            "OBJECT": "0x11ebad0505941fc8ad05847beb4a5184",
            "FORMATTER": "",
            "DISPLAYORDER": null,
            "LABELFLAG": "0",
            "UIDFLAG": "0",
            "HIDDENFLAG": "0",
            "EDITABLEFLAG": "0",
            "REQUIREDFLAG": "0",
            "RELATED_OBJ": "",
            "SORTERPOS": null,
            "SORTERDIR": "",
            "RELATED_OBJ_ATTR": "",
            "SHORT_DESCRIPTION": "Shorthand name by which the End-User wishes to be referred to at the RP, such as janedoe or j.doe. This value MAY be any valid JSON string including special characters such as @, \/, or whitespace. Not neccessarily unique!!!",
            "DATA_ADDRESS_PROPS": null,
            "DEFAULT_VALUE": "",
            "FIXED_VALUE": "",
            "CUSTOM_DATA_TYPE": null
        },
        {
            "CREATED_ON": "2021-01-21 18:04:20",
            "MODIFIED_ON": "2021-01-21 18:04:20",
            "CREATED_BY_USER": "0x31000000000000000000000000000000",
            "MODIFIED_BY_USER": "0x31000000000000000000000000000000",
            "UID": "0x11eba154b4129636a154025041000001",
            "SORTABLEFLAG": "1",
            "FILTERABLEFLAG": "1",
            "AGGREGATABLEFLAG": "1",
            "DEFAULT_AGGREGATE_FUNCTION": "",
            "VALUE_LIST_DELIMITER": ",",
            "READABLEFLAG": "1",
            "WRITABLEFLAG": "0",
            "SYSTEMFLAG": "0",
            "DEFAULT_EDITOR_UXON": null,
            "COPY_WITH_RELATED_OBJECT": "0",
            "DELETE_WITH_RELATED_OBJECT": "0",
            "DEFAULT_DISPLAY_UXON": null,
            "COMMENTS": "",
            "NAME": "Profile",
            "RELATION_CARDINALITY": "",
            "TYPE": "D",
            "COPYABLEFLAG": "0",
            "ALIAS": "profile",
            "DATATYPE": "0x31320000000000000000000000000000",
            "DATA_ADDRESS": "profile",
            "OBJECT": "0x11ebad0505941fc8ad05847beb4a5184",
            "FORMATTER": "",
            "DISPLAYORDER": null,
            "LABELFLAG": "0",
            "UIDFLAG": "0",
            "HIDDENFLAG": "0",
            "EDITABLEFLAG": "0",
            "REQUIREDFLAG": "0",
            "RELATED_OBJ": "",
            "SORTERPOS": null,
            "SORTERDIR": "",
            "RELATED_OBJ_ATTR": "",
            "SHORT_DESCRIPTION": "URL of the End-User's profile page. The contents of this Web page SHOULD be about the End-User.\n",
            "DATA_ADDRESS_PROPS": null,
            "DEFAULT_VALUE": "",
            "FIXED_VALUE": "",
            "CUSTOM_DATA_TYPE": null
        },
        {
            "CREATED_ON": "2021-01-21 18:04:49",
            "MODIFIED_ON": "2021-01-21 18:05:07",
            "CREATED_BY_USER": "0x31000000000000000000000000000000",
            "MODIFIED_BY_USER": "0x31000000000000000000000000000000",
            "UID": "0x11ebb7a3c5aca454b7a3025041000001",
            "SORTABLEFLAG": "1",
            "FILTERABLEFLAG": "1",
            "AGGREGATABLEFLAG": "1",
            "DEFAULT_AGGREGATE_FUNCTION": "",
            "VALUE_LIST_DELIMITER": ",",
            "READABLEFLAG": "1",
            "WRITABLEFLAG": "0",
            "SYSTEMFLAG": "0",
            "DEFAULT_EDITOR_UXON": null,
            "COPY_WITH_RELATED_OBJECT": "0",
            "DELETE_WITH_RELATED_OBJECT": "0",
            "DEFAULT_DISPLAY_UXON": null,
            "COMMENTS": "",
            "NAME": "Picture",
            "RELATION_CARDINALITY": "",
            "TYPE": "D",
            "COPYABLEFLAG": "0",
            "ALIAS": "picture",
            "DATATYPE": "0x31350000000000000000000000000000",
            "DATA_ADDRESS": "picture",
            "OBJECT": "0x11ebad0505941fc8ad05847beb4a5184",
            "FORMATTER": "",
            "DISPLAYORDER": null,
            "LABELFLAG": "0",
            "UIDFLAG": "0",
            "HIDDENFLAG": "0",
            "EDITABLEFLAG": "0",
            "REQUIREDFLAG": "0",
            "RELATED_OBJ": "",
            "SORTERPOS": null,
            "SORTERDIR": "",
            "RELATED_OBJ_ATTR": "",
            "SHORT_DESCRIPTION": "URL of the End-User's profile picture. This URL MUST refer to an image file (for example, a PNG, JPEG, or GIF image file), rather than to a Web page containing an image. Note that this URL SHOULD specifically reference a profile photo of the End-User suitable for displaying when describing the End-User, rather than an arbitrary photo taken by the End-User.\n",
            "DATA_ADDRESS_PROPS": null,
            "DEFAULT_VALUE": "",
            "FIXED_VALUE": "",
            "CUSTOM_DATA_TYPE": null
        },
        {
            "CREATED_ON": "2021-01-21 18:05:45",
            "MODIFIED_ON": "2021-01-21 18:05:45",
            "CREATED_BY_USER": "0x31000000000000000000000000000000",
            "MODIFIED_BY_USER": "0x31000000000000000000000000000000",
            "UID": "0x11ebb55fe6a49220b55f025041000001",
            "SORTABLEFLAG": "1",
            "FILTERABLEFLAG": "1",
            "AGGREGATABLEFLAG": "1",
            "DEFAULT_AGGREGATE_FUNCTION": "",
            "VALUE_LIST_DELIMITER": ",",
            "READABLEFLAG": "1",
            "WRITABLEFLAG": "0",
            "SYSTEMFLAG": "0",
            "DEFAULT_EDITOR_UXON": null,
            "COPY_WITH_RELATED_OBJECT": "0",
            "DELETE_WITH_RELATED_OBJECT": "0",
            "DEFAULT_DISPLAY_UXON": null,
            "COMMENTS": "",
            "NAME": "Website",
            "RELATION_CARDINALITY": "",
            "TYPE": "D",
            "COPYABLEFLAG": "0",
            "ALIAS": "website",
            "DATATYPE": "0x31320000000000000000000000000000",
            "DATA_ADDRESS": "website",
            "OBJECT": "0x11ebad0505941fc8ad05847beb4a5184",
            "FORMATTER": "",
            "DISPLAYORDER": null,
            "LABELFLAG": "0",
            "UIDFLAG": "0",
            "HIDDENFLAG": "0",
            "EDITABLEFLAG": "0",
            "REQUIREDFLAG": "0",
            "RELATED_OBJ": "",
            "SORTERPOS": null,
            "SORTERDIR": "",
            "RELATED_OBJ_ATTR": "",
            "SHORT_DESCRIPTION": "URL of the End-User's Web page or blog. This Web page SHOULD contain information published by the End-User or an organization that the End-User is affiliated with.\n",
            "DATA_ADDRESS_PROPS": null,
            "DEFAULT_VALUE": "",
            "FIXED_VALUE": "",
            "CUSTOM_DATA_TYPE": null
        },
        {
            "CREATED_ON": "2021-01-21 18:06:38",
            "MODIFIED_ON": "2021-01-21 18:06:38",
            "CREATED_BY_USER": "0x31000000000000000000000000000000",
            "MODIFIED_BY_USER": "0x31000000000000000000000000000000",
            "UID": "0x11eb98d5069d976698d5025041000001",
            "SORTABLEFLAG": "1",
            "FILTERABLEFLAG": "1",
            "AGGREGATABLEFLAG": "1",
            "DEFAULT_AGGREGATE_FUNCTION": "",
            "VALUE_LIST_DELIMITER": ",",
            "READABLEFLAG": "1",
            "WRITABLEFLAG": "0",
            "SYSTEMFLAG": "0",
            "DEFAULT_EDITOR_UXON": null,
            "COPY_WITH_RELATED_OBJECT": "0",
            "DELETE_WITH_RELATED_OBJECT": "0",
            "DEFAULT_DISPLAY_UXON": null,
            "COMMENTS": "",
            "NAME": "Email",
            "RELATION_CARDINALITY": "",
            "TYPE": "D",
            "COPYABLEFLAG": "0",
            "ALIAS": "email",
            "DATATYPE": "0x30000000000000000000000000000000",
            "DATA_ADDRESS": "email",
            "OBJECT": "0x11ebad0505941fc8ad05847beb4a5184",
            "FORMATTER": "",
            "DISPLAYORDER": null,
            "LABELFLAG": "0",
            "UIDFLAG": "0",
            "HIDDENFLAG": "0",
            "EDITABLEFLAG": "0",
            "REQUIREDFLAG": "0",
            "RELATED_OBJ": "",
            "SORTERPOS": null,
            "SORTERDIR": "",
            "RELATED_OBJ_ATTR": "",
            "SHORT_DESCRIPTION": "End-User's preferred e-mail address.",
            "DATA_ADDRESS_PROPS": null,
            "DEFAULT_VALUE": "",
            "FIXED_VALUE": "",
            "CUSTOM_DATA_TYPE": null
        },
        {
            "CREATED_ON": "2021-01-21 18:07:45",
            "MODIFIED_ON": "2021-01-21 18:07:45",
            "CREATED_BY_USER": "0x31000000000000000000000000000000",
            "MODIFIED_BY_USER": "0x31000000000000000000000000000000",
            "UID": "0x11eb8e7d2e8d25988e7d025041000001",
            "SORTABLEFLAG": "1",
            "FILTERABLEFLAG": "1",
            "AGGREGATABLEFLAG": "1",
            "DEFAULT_AGGREGATE_FUNCTION": "",
            "VALUE_LIST_DELIMITER": ",",
            "READABLEFLAG": "1",
            "WRITABLEFLAG": "0",
            "SYSTEMFLAG": "0",
            "DEFAULT_EDITOR_UXON": null,
            "COPY_WITH_RELATED_OBJECT": "0",
            "DELETE_WITH_RELATED_OBJECT": "0",
            "DEFAULT_DISPLAY_UXON": null,
            "COMMENTS": "",
            "NAME": "Email Verified",
            "RELATION_CARDINALITY": "",
            "TYPE": "D",
            "COPYABLEFLAG": "0",
            "ALIAS": "email_verified",
            "DATATYPE": "0x37000000000000000000000000000000",
            "DATA_ADDRESS": "email_verified",
            "OBJECT": "0x11ebad0505941fc8ad05847beb4a5184",
            "FORMATTER": "",
            "DISPLAYORDER": null,
            "LABELFLAG": "0",
            "UIDFLAG": "0",
            "HIDDENFLAG": "0",
            "EDITABLEFLAG": "0",
            "REQUIREDFLAG": "0",
            "RELATED_OBJ": "",
            "SORTERPOS": null,
            "SORTERDIR": "",
            "RELATED_OBJ_ATTR": "",
            "SHORT_DESCRIPTION": "When this Claim Value is true, this means that the OP took affirmative steps to ensure that this e-mail address was controlled by the End-User at the time the verification was performed. The means by which an e-mail address is verified is context-specific, and dependent upon the trust framework or contractual agreements within which the parties are operating.",
            "DATA_ADDRESS_PROPS": null,
            "DEFAULT_VALUE": "",
            "FIXED_VALUE": "",
            "CUSTOM_DATA_TYPE": null
        },
        {
            "CREATED_ON": "2021-01-21 18:08:09",
            "MODIFIED_ON": "2021-01-21 18:08:09",
            "CREATED_BY_USER": "0x31000000000000000000000000000000",
            "MODIFIED_BY_USER": "0x31000000000000000000000000000000",
            "UID": "0x11ebb7693cbdfdaeb769025041000001",
            "SORTABLEFLAG": "1",
            "FILTERABLEFLAG": "1",
            "AGGREGATABLEFLAG": "1",
            "DEFAULT_AGGREGATE_FUNCTION": "",
            "VALUE_LIST_DELIMITER": ",",
            "READABLEFLAG": "1",
            "WRITABLEFLAG": "0",
            "SYSTEMFLAG": "0",
            "DEFAULT_EDITOR_UXON": null,
            "COPY_WITH_RELATED_OBJECT": "0",
            "DELETE_WITH_RELATED_OBJECT": "0",
            "DEFAULT_DISPLAY_UXON": null,
            "COMMENTS": "",
            "NAME": "Gender",
            "RELATION_CARDINALITY": "",
            "TYPE": "D",
            "COPYABLEFLAG": "0",
            "ALIAS": "gender",
            "DATATYPE": "0x30000000000000000000000000000000",
            "DATA_ADDRESS": "gender",
            "OBJECT": "0x11ebad0505941fc8ad05847beb4a5184",
            "FORMATTER": "",
            "DISPLAYORDER": null,
            "LABELFLAG": "0",
            "UIDFLAG": "0",
            "HIDDENFLAG": "0",
            "EDITABLEFLAG": "0",
            "REQUIREDFLAG": "0",
            "RELATED_OBJ": "",
            "SORTERPOS": null,
            "SORTERDIR": "",
            "RELATED_OBJ_ATTR": "",
            "SHORT_DESCRIPTION": "End-User's gender. Values defined by this specification are female and male. Other values MAY be used when neither of the defined values are applicable.",
            "DATA_ADDRESS_PROPS": null,
            "DEFAULT_VALUE": "",
            "FIXED_VALUE": "",
            "CUSTOM_DATA_TYPE": null
        },
        {
            "CREATED_ON": "2021-01-21 18:09:02",
            "MODIFIED_ON": "2021-01-21 18:09:02",
            "CREATED_BY_USER": "0x31000000000000000000000000000000",
            "MODIFIED_BY_USER": "0x31000000000000000000000000000000",
            "UID": "0x11eba49b5c1054cca49b025041000001",
            "SORTABLEFLAG": "1",
            "FILTERABLEFLAG": "1",
            "AGGREGATABLEFLAG": "1",
            "DEFAULT_AGGREGATE_FUNCTION": "",
            "VALUE_LIST_DELIMITER": ",",
            "READABLEFLAG": "1",
            "WRITABLEFLAG": "0",
            "SYSTEMFLAG": "0",
            "DEFAULT_EDITOR_UXON": null,
            "COPY_WITH_RELATED_OBJECT": "0",
            "DELETE_WITH_RELATED_OBJECT": "0",
            "DEFAULT_DISPLAY_UXON": null,
            "COMMENTS": "",
            "NAME": "Birthdate",
            "RELATION_CARDINALITY": "",
            "TYPE": "D",
            "COPYABLEFLAG": "0",
            "ALIAS": "birthdate",
            "DATATYPE": "0x32000000000000000000000000000000",
            "DATA_ADDRESS": "birthdate",
            "OBJECT": "0x11ebad0505941fc8ad05847beb4a5184",
            "FORMATTER": "",
            "DISPLAYORDER": null,
            "LABELFLAG": "0",
            "UIDFLAG": "0",
            "HIDDENFLAG": "0",
            "EDITABLEFLAG": "0",
            "REQUIREDFLAG": "0",
            "RELATED_OBJ": "",
            "SORTERPOS": null,
            "SORTERDIR": "",
            "RELATED_OBJ_ATTR": "",
            "SHORT_DESCRIPTION": "End-User's birthday. The year MAY be 0000, indicating that it is omitted. To represent only the year, YYYY format is allowed. Note that depending on the underlying platform's date related function, providing just year can result in varying month and day, so the implementers need to take this factor into account to correctly process the dates.",
            "DATA_ADDRESS_PROPS": null,
            "DEFAULT_VALUE": "",
            "FIXED_VALUE": "",
            "CUSTOM_DATA_TYPE": null
        },
        {
            "CREATED_ON": "2021-01-21 18:09:31",
            "MODIFIED_ON": "2021-01-21 18:09:31",
            "CREATED_BY_USER": "0x31000000000000000000000000000000",
            "MODIFIED_BY_USER": "0x31000000000000000000000000000000",
            "UID": "0x11eb86966d8921708696025041000001",
            "SORTABLEFLAG": "1",
            "FILTERABLEFLAG": "1",
            "AGGREGATABLEFLAG": "1",
            "DEFAULT_AGGREGATE_FUNCTION": "",
            "VALUE_LIST_DELIMITER": ",",
            "READABLEFLAG": "1",
            "WRITABLEFLAG": "0",
            "SYSTEMFLAG": "0",
            "DEFAULT_EDITOR_UXON": null,
            "COPY_WITH_RELATED_OBJECT": "0",
            "DELETE_WITH_RELATED_OBJECT": "0",
            "DEFAULT_DISPLAY_UXON": null,
            "COMMENTS": "",
            "NAME": "Zoneinfo",
            "RELATION_CARDINALITY": "",
            "TYPE": "D",
            "COPYABLEFLAG": "0",
            "ALIAS": "zoneinfo",
            "DATATYPE": "0x30000000000000000000000000000000",
            "DATA_ADDRESS": "zoneinfo",
            "OBJECT": "0x11ebad0505941fc8ad05847beb4a5184",
            "FORMATTER": "",
            "DISPLAYORDER": null,
            "LABELFLAG": "0",
            "UIDFLAG": "0",
            "HIDDENFLAG": "0",
            "EDITABLEFLAG": "0",
            "REQUIREDFLAG": "0",
            "RELATED_OBJ": "",
            "SORTERPOS": null,
            "SORTERDIR": "",
            "RELATED_OBJ_ATTR": "",
            "SHORT_DESCRIPTION": "String from zoneinfo [zoneinfo] time zone database representing the End-User's time zone. For example, Europe\/Paris or America\/Los_Angeles.",
            "DATA_ADDRESS_PROPS": null,
            "DEFAULT_VALUE": "",
            "FIXED_VALUE": "",
            "CUSTOM_DATA_TYPE": null
        },
        {
            "CREATED_ON": "2021-01-21 18:10:26",
            "MODIFIED_ON": "2021-01-21 18:10:26",
            "CREATED_BY_USER": "0x31000000000000000000000000000000",
            "MODIFIED_BY_USER": "0x31000000000000000000000000000000",
            "UID": "0x11eb9d1b8e8c75349d1b025041000001",
            "SORTABLEFLAG": "1",
            "FILTERABLEFLAG": "1",
            "AGGREGATABLEFLAG": "1",
            "DEFAULT_AGGREGATE_FUNCTION": "",
            "VALUE_LIST_DELIMITER": ",",
            "READABLEFLAG": "1",
            "WRITABLEFLAG": "0",
            "SYSTEMFLAG": "0",
            "DEFAULT_EDITOR_UXON": null,
            "COPY_WITH_RELATED_OBJECT": "0",
            "DELETE_WITH_RELATED_OBJECT": "0",
            "DEFAULT_DISPLAY_UXON": null,
            "COMMENTS": "",
            "NAME": "Locale",
            "RELATION_CARDINALITY": "",
            "TYPE": "D",
            "COPYABLEFLAG": "0",
            "ALIAS": "locale",
            "DATATYPE": "0x30000000000000000000000000000000",
            "DATA_ADDRESS": "locale",
            "OBJECT": "0x11ebad0505941fc8ad05847beb4a5184",
            "FORMATTER": "",
            "DISPLAYORDER": null,
            "LABELFLAG": "0",
            "UIDFLAG": "0",
            "HIDDENFLAG": "0",
            "EDITABLEFLAG": "0",
            "REQUIREDFLAG": "0",
            "RELATED_OBJ": "",
            "SORTERPOS": null,
            "SORTERDIR": "",
            "RELATED_OBJ_ATTR": "",
            "SHORT_DESCRIPTION": "End-User's locale, represented as a BCP47 [RFC5646] language tag. For example, en-US or fr-CA. ",
            "DATA_ADDRESS_PROPS": null,
            "DEFAULT_VALUE": "",
            "FIXED_VALUE": "",
            "CUSTOM_DATA_TYPE": null
        },
        {
            "CREATED_ON": "2021-01-21 18:11:20",
            "MODIFIED_ON": "2021-01-21 18:11:20",
            "CREATED_BY_USER": "0x31000000000000000000000000000000",
            "MODIFIED_BY_USER": "0x31000000000000000000000000000000",
            "UID": "0x11eba40aae86aa1ca40a025041000001",
            "SORTABLEFLAG": "1",
            "FILTERABLEFLAG": "1",
            "AGGREGATABLEFLAG": "1",
            "DEFAULT_AGGREGATE_FUNCTION": "",
            "VALUE_LIST_DELIMITER": ",",
            "READABLEFLAG": "1",
            "WRITABLEFLAG": "0",
            "SYSTEMFLAG": "0",
            "DEFAULT_EDITOR_UXON": null,
            "COPY_WITH_RELATED_OBJECT": "0",
            "DELETE_WITH_RELATED_OBJECT": "0",
            "DEFAULT_DISPLAY_UXON": null,
            "COMMENTS": "",
            "NAME": "Updated at",
            "RELATION_CARDINALITY": "",
            "TYPE": "D",
            "COPYABLEFLAG": "0",
            "ALIAS": "updated_at",
            "DATATYPE": "0x33000000000000000000000000000000",
            "DATA_ADDRESS": "updated_at",
            "OBJECT": "0x11ebad0505941fc8ad05847beb4a5184",
            "FORMATTER": "",
            "DISPLAYORDER": null,
            "LABELFLAG": "0",
            "UIDFLAG": "0",
            "HIDDENFLAG": "0",
            "EDITABLEFLAG": "0",
            "REQUIREDFLAG": "0",
            "RELATED_OBJ": "",
            "SORTERPOS": null,
            "SORTERDIR": "",
            "RELATED_OBJ_ATTR": "",
            "SHORT_DESCRIPTION": "Time the End-User's information was last updated.\n",
            "DATA_ADDRESS_PROPS": null,
            "DEFAULT_VALUE": "",
            "FIXED_VALUE": "",
            "CUSTOM_DATA_TYPE": null
        }
    ],
    "totals_rows": [],
    "filters": {
        "operator": "AND",
        "base_object_alias": "exface.Core.ATTRIBUTE",
        "conditions": [
            {
                "expression": "OBJECT__APP",
                "comparator": "=",
                "value": "0x11ebb9fe152517a0b9fe847beb4a5184",
                "object_alias": "exface.Core.ATTRIBUTE"
            }
        ]
    },
    "rows_limit": null,
    "rows_offset": 0,
    "sorters": [
        {
            "attribute_alias": "CREATED_ON",
            "direction": "ASC"
        },
        {
            "attribute_alias": "UID",
            "direction": "ASC"
        }
    ]
}